zope.interface-7.0.3-py3.10-nspkg.pth
zope/interface/advice.py
zope/interface/interface.py
zope/interface/registry.py
zope/interface/document.py
zope/interface/_compat.py
zope/interface/_flatten.py
zope/interface/declarations.py
zope/interface/exceptions.py
zope/interface/__init__.py
zope/interface/interfaces.py
zope/interface/_zope_interface_coptimizations.cpython-310-x86_64-linux-gnu.so
zope/interface/ro.py
zope/interface/_zope_interface_coptimizations.c
zope/interface/verify.py
zope/interface/adapter.py
zope/interface/tests/test_interface.py
zope/interface/tests/advisory_testing.py
zope/interface/tests/test_interfaces.py
zope/interface/tests/test_registry.py
zope/interface/tests/test_advice.py
zope/interface/tests/test_element.py
zope/interface/tests/test_odd_declarations.py
zope/interface/tests/idummy.py
zope/interface/tests/test_compile_flags.py
zope/interface/tests/test_declarations.py
zope/interface/tests/__init__.py
zope/interface/tests/test_verify.py
zope/interface/tests/m1.py
zope/interface/tests/odd.py
zope/interface/tests/test_sorting.py
zope/interface/tests/test_adapter.py
zope/interface/tests/test_document.py
zope/interface/tests/test_exceptions.py
zope/interface/tests/test_ro.py
zope/interface/tests/dummy.py
zope/interface/common/mapping.py
zope/interface/common/sequence.py
zope/interface/common/idatetime.py
zope/interface/common/builtins.py
zope/interface/common/numbers.py
zope/interface/common/io.py
zope/interface/common/__init__.py
zope/interface/common/interfaces.py
zope/interface/common/collections.py
zope/interface/common/tests/test_idatetime.py
zope/interface/common/tests/test_collections.py
zope/interface/common/tests/__init__.py
zope/interface/common/tests/test_numbers.py
zope/interface/common/tests/test_io.py
zope/interface/common/tests/test_builtins.py
zope/interface/common/tests/test_import_interfaces.py
zope/interface/common/tests/basemapping.py
zope.interface-7.0.3.dist-info/RECORD
zope.interface-7.0.3.dist-info/WHEEL
zope.interface-7.0.3.dist-info/top_level.txt
zope.interface-7.0.3.dist-info/namespace_packages.txt
zope.interface-7.0.3.dist-info/LICENSE.txt
zope.interface-7.0.3.dist-info/METADATA
