Metadata-Version: 2.1
Name: zope.interface
Version: 7.0.3
Summary: Interfaces for Python
Home-page: https://github.com/zopefoundation/zope.interface
Author: Zope Foundation and Contributors
Author-email: zope-dev@zope.org
License: ZPL 2.1
Keywords: interface,components,plugins
Classifier: Development Status :: 5 - Production/Stable
Classifier: Intended Audience :: Developers
Classifier: License :: OSI Approved :: Zope Public License
Classifier: Operating System :: OS Independent
Classifier: Programming Language :: Python
Classifier: Programming Language :: Python :: 3
Classifier: Programming Language :: Python :: 3.8
Classifier: Programming Language :: Python :: 3.9
Classifier: Programming Language :: Python :: 3.10
Classifier: Programming Language :: Python :: 3.11
Classifier: Programming Language :: Python :: 3.12
Classifier: Programming Language :: Python :: Implementation :: CPython
Classifier: Programming Language :: Python :: Implementation :: PyPy
Classifier: Framework :: Zope :: 3
Classifier: Topic :: Software Development :: Libraries :: Python Modules
Requires-Python: >=3.8
License-File: LICENSE.txt
Requires-Dist: setuptools
Provides-Extra: docs
Requires-Dist: Sphinx ; extra == 'docs'
Requires-Dist: repoze.sphinx.autointerface ; extra == 'docs'
Requires-Dist: sphinx-rtd-theme ; extra == 'docs'
Provides-Extra: test
Requires-Dist: coverage >=5.0.3 ; extra == 'test'
Requires-Dist: zope.event ; extra == 'test'
Requires-Dist: zope.testing ; extra == 'test'
Provides-Extra: testing
Requires-Dist: coverage >=5.0.3 ; extra == 'testing'
Requires-Dist: zope.event ; extra == 'testing'
Requires-Dist: zope.testing ; extra == 'testing'
